not_dead_yet/__init__.py
not_dead_yet/__main__.py
not_dead_yet/notifier.py
not_dead_yet/resource.py
not_dead_yet/serve.py
not_dead_yet/watcher.py
not_dead_yet/ws.py
not_dead_yet-0.5.0.dist-info/METADATA
not_dead_yet-0.5.0.dist-info/WHEEL
not_dead_yet-0.5.0.dist-info/entry_points.txt
not_dead_yet-0.5.0.dist-info/RECORD
